{
  "RawInvoices": [
    {
      "Invoice No": "352353/1",
      "Type": "Invoice",
      "Invoice Date": "20.09.21",
      "Bill of Lading": "202101073253103",
      "Customer": "NILLE AS",
      "Customer Address": "POSTBOKS 530 BEDRIFTSSENTERET,1411 KOLBOTN",
      "Customer Number": "10112",
      "ETD": "13.09.21",
      "POL": "IN-TUT TUTICORIN",
      "POD": "NO-MSS MOSS",
      "Total": 65229.75,
      "VAT": 78.75,
      "NetValue": 65151.0,
      "Currency": "NOK",
      "Reference No.": "A.ref 506370",
      "Due Date": "19.11.21",
      "Tour Number": "10/0178273/STH"
    },
    {
      "Invoice No": "352353/2",
      "Type": "Invoice",
      "Invoice Date": "20.09.21",
      "Bill of Lading": "202102222254001",
      "Customer": "NILLE AS",
      "Customer Address": "POSTBOKS 530 BEDRIFTSSENTERET,1411 KOLBOTN",
      "Customer Number": "10112",
      "ETD": "13.09.21",
      "POL": "CN-NPO NINGBO",
      "POD": "NO-MSS MOSS",
      "Total": 119770.75,
      "VAT": 78.75,
      "NetValue": 119692.0,
      "Currency": "NOK",
      "Reference No.": "A.ref 506315",
      "Due Date": "19.11.21",
      "Tour Number": "10/0178813/STH"
    },
    {
      "Invoice No": "352353/3",
      "Type": "Invoice",
      "Invoice Date": "20.09.21",
      "Bill of Lading": "202102037259001 SEPTEMBER",
      "Customer": "NILLE AS",
      "Customer Address": "POSTBOKS 530 BEDRIFTSSENTERET,1411 KOLBOTN",
      "Customer Number": "10112",
      "ETD": "20.09.21",
      "POL": "IN-MUN MUNDRA",
      "POD": "NO-MSS MOSS",
      "Total": 39186.75,
      "VAT": 78.75,
      "NetValue": 39108.0,
      "Currency": "NOK",
      "Reference No.": "A.ref 506754",
      "Due Date": "19.11.21",
      "Tour Number": "10/0181606/STH"
    },
    {
      "Invoice No": "352353/4",
      "Type": "Invoice",
      "Invoice Date": "20.09.21",
      "Bill of Lading": "202106211258003 SEPTEMBER",
      "Customer": "NILLE AS",
      "Customer Address": "POSTBOKS 530 BEDRIFTSSENTERET,1411 KOLBOTN",
      "Customer Number": "10112",
      "ETD": "16.09.21",
      "POL": "PK-KHI KARACHI",
      "POD": "NO-DRM DRAMMEN",
      "Total": 25828.75,
      "VAT": 78.75,
      "NetValue": 25750.0,
      "Currency": "NOK",
      "Reference No.": "A.ref 506868",
      "Due Date": "19.11.21",
      "Tour Number": "10/0182643/STH"
    },
    {
      "Invoice No": "352353/5",
      "Type": "Invoice",
      "Invoice Date": "20.09.21",
      "Bill of Lading": "202101062253003 SEPTEMBER",
      "Customer": "NILLE AS",
      "Customer Address": "POSTBOKS 530 BEDRIFTSSENTERET,1411 KOLBOTN",
      "Customer Number": "10112",
      "ETD": "10.09.21",
      "POL": "IN-NSA NHAVA SHEVA",
      "POD": "NO-OSL OSLO",
      "Total": 30358.75,
      "VAT": 78.75,
      "NetValue": 30280.0,
      "Currency": "NOK",
      "Reference No.": "A.ref 506658",
      "Due Date": "19.11.21",
      "Tour Number": "10/0182646/STH"
    }
  ],
  "RawInvoiceCharges": [
    {
      "Invoice": "352353/1",
      "Charge Type": "FORTOLLING MEDUMQ146174",
      "Unit Price": 265.0,
      "Currency": "NOK",
      "Exchange Rate": 1.0,
      "Total": 331.25,
      "Currency Total": "NOK",
      "VAT": 66.25,
      "VAT Percentage": "25.0%"
    },
    {
      "Invoice": "352353/1",
      "Charge Type": "MVA BLANKETT",
      "Unit Price": 50.0,
      "Currency": "NOK",
      "Exchange Rate": 1.0,
      "Total": 62.5,
      "Currency Total": "NOK",
      "VAT": 12.5,
      "VAT Percentage": "25.0%"
    },
    {
      "Invoice": "352353/1",
      "Charge Type": "SJ\u00d8FR 20'+ 4H' 13/7",
      "Unit Price": 6750.0,
      "Currency": "USD",
      "Exchange Rate": 8.9974,
      "Total": 60732.0,
      "Currency Total": "NOK",
      "VAT": 0.0
    },
    {
      "Invoice": "352353/1",
      "Charge Type": "THC",
      "Unit Price": 2050.0,
      "Currency": "NOK",
      "Exchange Rate": 1.0,
      "Total": 2050.0,
      "Currency Total": "NOK",
      "VAT": 0.0
    },
    {
      "Invoice": "352353/1",
      "Charge Type": "VARE-/HAVNEAVGIFT",
      "Unit Price": 850.0,
      "Currency": "NOK",
      "Exchange Rate": 1.0,
      "Total": 850.0,
      "Currency Total": "NOK",
      "VAT": 0.0
    },
    {
      "Invoice": "352353/1",
      "Charge Type": "B/L & DOKUMENTASJON",
      "Unit Price": 475.0,
      "Currency": "NOK",
      "Exchange Rate": 1.0,
      "Total": 475.0,
      "Currency Total": "NOK",
      "VAT": 0.0
    },
    {
      "Invoice": "352353/1",
      "Charge Type": "SECA",
      "Unit Price": 81.0,
      "Currency": "USD",
      "Exchange Rate": 8.9974,
      "Total": 729.0,
      "Currency Total": "NOK",
      "VAT": 0.0
    },
    {
      "Invoice": "352353/2",
      "Charge Type": "FORTOLLING 211502210",
      "Unit Price": 265.0,
      "Currency": "NOK",
      "Exchange Rate": 1.0,
      "Total": 331.25,
      "Currency Total": "NOK",
      "VAT": 66.25,
      "VAT Percentage": "25.0%"
    },
    {
      "Invoice": "352353/2",
      "Charge Type": "MVA BLANKETT",
      "Unit Price": 50.0,
      "Currency": "NOK",
      "Exchange Rate": 1.0,
      "Total": 62.5,
      "Currency Total": "NOK",
      "VAT": 12.5,
      "VAT Percentage": "25.0%"
    },
    {
      "Invoice": "352353/2",
      "Charge Type": "SJ\u00d8FR. 1X45'HC 18/7",
      "Unit Price": 13000.0,
      "Currency": "USD",
      "Exchange Rate": 8.9974,
      "Total": 116966.0,
      "Currency Total": "NOK",
      "VAT": 0.0
    },
    {
      "Invoice": "352353/2",
      "Charge Type": "THC",
      "Unit Price": 1025.0,
      "Currency": "NOK",
      "Exchange Rate": 1.0,
      "Total": 1025.0,
      "Currency Total": "NOK",
      "VAT": 0.0
    },
    {
      "Invoice": "352353/2",
      "Charge Type": "VARE-/HAVNEAVGIFT",
      "Unit Price": 425.0,
      "Currency": "NOK",
      "Exchange Rate": 1.0,
      "Total": 425.0,
      "Currency Total": "NOK",
      "VAT": 0.0
    },
    {
      "Invoice": "352353/2",
      "Charge Type": "B/L & DOKUMENTASJON",
      "Unit Price": 475.0,
      "Currency": "NOK",
      "Exchange Rate": 1.0,
      "Total": 475.0,
      "Currency Total": "NOK",
      "VAT": 0.0
    },
    {
      "Invoice": "352353/2",
      "Charge Type": "SECA",
      "Unit Price": 54.0,
      "Currency": "USD",
      "Exchange Rate": 8.9974,
      "Total": 486.0,
      "Currency Total": "NOK",
      "VAT": 0.0
    },
    {
      "Invoice": "352353/3",
      "Charge Type": "FORTOLLING MEDUMQ513217",
      "Unit Price": 265.0,
      "Currency": "NOK",
      "Exchange Rate": 1.0,
      "Total": 331.25,
      "Currency Total": "NOK",
      "VAT": 66.25,
      "VAT Percentage": "25.0%"
    },
    {
      "Invoice": "352353/3",
      "Charge Type": "MVA BLANKETT",
      "Unit Price": 50.0,
      "Currency": "NOK",
      "Exchange Rate": 1.0,
      "Total": 62.5,
      "Currency Total": "NOK",
      "VAT": 12.5,
      "VAT Percentage": "25.0%"
    },
    {
      "Invoice": "352353/3",
      "Charge Type": "SJ\u00d8FR 1X40'DC 5/8",
      "Unit Price": 4050.0,
      "Currency": "USD",
      "Exchange Rate": 8.9834,
      "Total": 36383.0,
      "Currency Total": "NOK",
      "VAT": 0.0
    },
    {
      "Invoice": "352353/3",
      "Charge Type": "THC",
      "Unit Price": 1025.0,
      "Currency": "NOK",
      "Exchange Rate": 1.0,
      "Total": 1025.0,
      "Currency Total": "NOK",
      "VAT": 0.0
    },
    {
      "Invoice": "352353/3",
      "Charge Type": "VARE-/HAVNEAVGIFT",
      "Unit Price": 425.0,
      "Currency": "NOK",
      "Exchange Rate": 1.0,
      "Total": 425.0,
      "Currency Total": "NOK",
      "VAT": 0.0
    },
    {
      "Invoice": "352353/3",
      "Charge Type": "B/L & DOKUMENTASJON",
      "Unit Price": 475.0,
      "Currency": "NOK",
      "Exchange Rate": 1.0,
      "Total": 475.0,
      "Currency Total": "NOK",
      "VAT": 0.0
    },
    {
      "Invoice": "352353/3",
      "Charge Type": "SECA",
      "Unit Price": 54.0,
      "Currency": "USD",
      "Exchange Rate": 8.9834,
      "Total": 485.0,
      "Currency Total": "NOK",
      "VAT": 0.0
    },
    {
      "Invoice": "352353/4",
      "Charge Type": "FORTOLLING 212425128",
      "Unit Price": 265.0,
      "Currency": "NOK",
      "Exchange Rate": 1.0,
      "Total": 331.25,
      "Currency Total": "NOK",
      "VAT": 66.25,
      "VAT Percentage": "25.0%"
    },
    {
      "Invoice": "352353/4",
      "Charge Type": "MVA BLANKETT",
      "Unit Price": 50.0,
      "Currency": "NOK",
      "Exchange Rate": 1.0,
      "Total": 62.5,
      "Currency Total": "NOK",
      "VAT": 12.5,
      "VAT Percentage": "25.0%"
    },
    {
      "Invoice": "352353/4",
      "Charge Type": "SJ\u00d8FR 1X20'DC 10/8",
      "Unit Price": 2400.0,
      "Currency": "USD",
      "Exchange Rate": 8.9834,
      "Total": 21560.0,
      "Currency Total": "NOK",
      "VAT": 0.0
    },
    {
      "Invoice": "352353/4",
      "Charge Type": "THC",
      "Unit Price": 1025.0,
      "Currency": "NOK",
      "Exchange Rate": 1.0,
      "Total": 1025.0,
      "Currency Total": "NOK",
      "VAT": 0.0
    },
    {
      "Invoice": "352353/4",
      "Charge Type": "TOMRETUR MOSS",
      "Unit Price": 190.0,
      "Currency": "USD",
      "Exchange Rate": 8.9834,
      "Total": 1707.0,
      "Currency Total": "NOK",
      "VAT": 0.0
    },
    {
      "Invoice": "352353/4",
      "Charge Type": "VARE-/HAVNEAVGIFT",
      "Unit Price": 425.0,
      "Currency": "NOK",
      "Exchange Rate": 1.0,
      "Total": 425.0,
      "Currency Total": "NOK",
      "VAT": 0.0
    },
    {
      "Invoice": "352353/4",
      "Charge Type": "B/L & DOKUMENTASJON",
      "Unit Price": 475.0,
      "Currency": "NOK",
      "Exchange Rate": 1.0,
      "Total": 475.0,
      "Currency Total": "NOK",
      "VAT": 0.0
    },
    {
      "Invoice": "352353/4",
      "Charge Type": "SECA",
      "Unit Price": 27.0,
      "Currency": "USD",
      "Exchange Rate": 8.9834,
      "Total": 243.0,
      "Currency Total": "NOK",
      "VAT": 0.0
    },
    {
      "Invoice": "352353/5",
      "Charge Type": "FORTOLLING GNSAOSLG2103809",
      "Unit Price": 265.0,
      "Currency": "NOK",
      "Exchange Rate": 1.0,
      "Total": 331.25,
      "Currency Total": "NOK",
      "VAT": 66.25,
      "VAT Percentage": "25.0%"
    },
    {
      "Invoice": "352353/5",
      "Charge Type": "MVA BLANKETT",
      "Unit Price": 50.0,
      "Currency": "NOK",
      "Exchange Rate": 1.0,
      "Total": 62.5,
      "Currency Total": "NOK",
      "VAT": 12.5,
      "VAT Percentage": "25.0%"
    },
    {
      "Invoice": "352353/5",
      "Charge Type": "SJ\u00d8FR. LCL 8/8",
      "Unit Price": 3132.0,
      "Currency": "USD",
      "Exchange Rate": 8.9974,
      "Total": 28180.0,
      "Currency Total": "NOK",
      "VAT": 0.0
    },
    {
      "Invoice": "352353/5",
      "Charge Type": "THC",
      "Unit Price": 947.05,
      "Currency": "NOK",
      "Exchange Rate": 1.0,
      "Total": 947.0,
      "Currency Total": "NOK",
      "VAT": 0.0
    },
    {
      "Invoice": "352353/5",
      "Charge Type": "VARE-/HAVNEAVGIFT",
      "Unit Price": 35.0,
      "Currency": "NOK",
      "Exchange Rate": 1.0,
      "Total": 35.0,
      "Currency Total": "NOK",
      "VAT": 0.0
    },
    {
      "Invoice": "352353/5",
      "Charge Type": "B/L & DOKUMENTASJON",
      "Unit Price": 475.0,
      "Currency": "NOK",
      "Exchange Rate": 1.0,
      "Total": 475.0,
      "Currency Total": "NOK",
      "VAT": 0.0
    },
    {
      "Invoice": "352353/5",
      "Charge Type": "LCL CHARGE",
      "Unit Price": 327.54,
      "Currency": "NOK",
      "Exchange Rate": 1.0,
      "Total": 328.0,
      "Currency Total": "NOK",
      "VAT": 0.0
    }
  ]
}