{
  "RawInvoices": [
    {
      "Invoice No": "353505/1",
      "Type": "Invoice",
      "Invoice Date": "23.12.21",
      "Bill of Lading": "202102222335001",
      "Customer": "NILLE AS",
      "Customer Address": "POSTBOKS 530 BEDRIFTSSENTERET,1411 KOLBOTN",
      "Customer Number": "10112",
      "ETD": "2.12.21",
      "POL": "CN-NPO NINGBO",
      "POD": "NO-MSS MOSS",
      "Total": 165384.75,
      "VAT": 78.75,
      "NetValue": 165306.0,
      "Currency": "NOK",
      "Reference No.": "A.ref 506828",
      "Due Date": "21.02.22",
      "Tour Number": "10/0182252/STH"
    },
    {
      "Invoice No": "353505/2",
      "Type": "Invoice",
      "Invoice Date": "23.12.21",
      "Bill of Lading": "202102222335001",
      "Customer": "NILLE AS",
      "Customer Address": "POSTBOKS 530 BEDRIFTSSENTERET,1411 KOLBOTN",
      "Customer Number": "10112",
      "ETD": "2.12.21",
      "POL": "CN-NPO NINGBO",
      "POD": "NO-MSS MOSS",
      "Total": 169226.75,
      "VAT": 78.75,
      "NetValue": 169148.0,
      "Currency": "NOK",
      "Reference No.": "A.ref 506903-2",
      "Due Date": "21.02.22",
      "Tour Number": "10/0187018/STH"
    }
  ],
  "RawInvoiceCharges": [
    {
      "Invoice": "353505/1",
      "Charge Type": "FORTOLLING 143163032262",
      "Unit Price": 265.0,
      "Currency": "NOK",
      "Exchange Rate": 1.0,
      "Total": 331.25,
      "Currency Total": "NOK",
      "VAT": 66.25,
      "VAT Percentage": "25.0%"
    },
    {
      "Invoice": "353505/1",
      "Charge Type": "MVA BLANKETT",
      "Unit Price": 50.0,
      "Currency": "NOK",
      "Exchange Rate": 1.0,
      "Total": 62.5,
      "Currency Total": "NOK",
      "VAT": 12.5,
      "VAT Percentage": "25.0%"
    },
    {
      "Invoice": "353505/1",
      "Charge Type": "SJ\u00d8FR 1X40'HC 14/10",
      "Unit Price": 17300.0,
      "Currency": "USD",
      "Exchange Rate": 9.3964,
      "Total": 162558.0,
      "Currency Total": "NOK",
      "VAT": 0.0
    },
    {
      "Invoice": "353505/1",
      "Charge Type": "THC",
      "Unit Price": 1025.0,
      "Currency": "NOK",
      "Exchange Rate": 1.0,
      "Total": 1025.0,
      "Currency Total": "NOK",
      "VAT": 0.0
    },
    {
      "Invoice": "353505/1",
      "Charge Type": "VARE-/HAVNEAVGIFT",
      "Unit Price": 425.0,
      "Currency": "NOK",
      "Exchange Rate": 1.0,
      "Total": 425.0,
      "Currency Total": "NOK",
      "VAT": 0.0
    },
    {
      "Invoice": "353505/1",
      "Charge Type": "B/L & DOKUMENTASJON",
      "Unit Price": 475.0,
      "Currency": "NOK",
      "Exchange Rate": 1.0,
      "Total": 475.0,
      "Currency Total": "NOK",
      "VAT": 0.0
    },
    {
      "Invoice": "353505/1",
      "Charge Type": "SECA",
      "Unit Price": 54.0,
      "Currency": "USD",
      "Exchange Rate": 9.4132,
      "Total": 508.0,
      "Currency Total": "NOK",
      "VAT": 0.0
    },
    {
      "Invoice": "353505/2",
      "Charge Type": "FORTOLLING 143163032246",
      "Unit Price": 265.0,
      "Currency": "NOK",
      "Exchange Rate": 1.0,
      "Total": 331.25,
      "Currency Total": "NOK",
      "VAT": 66.25,
      "VAT Percentage": "25.0%"
    },
    {
      "Invoice": "353505/2",
      "Charge Type": "MVA BLANKETT",
      "Unit Price": 50.0,
      "Currency": "NOK",
      "Exchange Rate": 1.0,
      "Total": 62.5,
      "Currency Total": "NOK",
      "VAT": 12.5,
      "VAT Percentage": "25.0%"
    },
    {
      "Invoice": "353505/2",
      "Charge Type": "SJ\u00d8FR 1X40'HC 17/10",
      "Unit Price": 17300.0,
      "Currency": "USD",
      "Exchange Rate": 9.4132,
      "Total": 162848.0,
      "Currency Total": "NOK",
      "VAT": 0.0
    },
    {
      "Invoice": "353505/2",
      "Charge Type": "CONSOLIDATION FEE",
      "Unit Price": 125.0,
      "Currency": "USD",
      "Exchange Rate": 9.4132,
      "Total": 1177.0,
      "Currency Total": "NOK",
      "VAT": 0.0
    },
    {
      "Invoice": "353505/2",
      "Charge Type": "THC",
      "Unit Price": 1025.0,
      "Currency": "NOK",
      "Exchange Rate": 1.0,
      "Total": 1025.0,
      "Currency Total": "NOK",
      "VAT": 0.0
    },
    {
      "Invoice": "353505/2",
      "Charge Type": "VARE-/HAVNEAVGIFT",
      "Unit Price": 425.0,
      "Currency": "NOK",
      "Exchange Rate": 1.0,
      "Total": 425.0,
      "Currency Total": "NOK",
      "VAT": 0.0
    },
    {
      "Invoice": "353505/2",
      "Charge Type": "B/L & DOKUMENTASJON",
      "Unit Price": 2850.0,
      "Currency": "NOK",
      "Exchange Rate": 1.0,
      "Total": 2850.0,
      "Currency Total": "NOK",
      "VAT": 0.0
    },
    {
      "Invoice": "353505/2",
      "Charge Type": "SECA",
      "Unit Price": 54.0,
      "Currency": "USD",
      "Exchange Rate": 9.4132,
      "Total": 508.0,
      "Currency Total": "NOK",
      "VAT": 0.0
    }
  ]
}